nerf/__init__.py
nerf/__main__.py
nerf/dataloading.py
nerf/model.py
nerf/ray_helpers.py
nerf/rendering.py
nerf/train.py
jax_nerf-1.0.9.dist-info/LICENSE
jax_nerf-1.0.9.dist-info/METADATA
jax_nerf-1.0.9.dist-info/WHEEL
jax_nerf-1.0.9.dist-info/top_level.txt
jax_nerf-1.0.9.dist-info/RECORD
