Metadata-Version: 2.1
Name: jax-nerf
Version: 1.0.9
Summary: Jax implementation of neural radiance fields
Author-email: Pengfei Zhao <p.zhao.9000@gmail.com>
License: MIT License
Project-URL: Homepage, https://github.com/pzdkn/jax-nerf
Keywords: jax,nerf
Classifier: License :: OSI Approved :: MIT License
Requires-Python: >=3.8.10
License-File: LICENSE
Requires-Dist: jax (==0.3.25)
Requires-Dist: jaxlib (==0.3.25)
Requires-Dist: flax (==0.6.3)
Requires-Dist: optax (>=0.1.4)
Requires-Dist: Pillow (>=9.4.0)
Requires-Dist: numpy (==1.23.5)
Requires-Dist: tomli ; python_version < "3.11"
Provides-Extra: dev
Requires-Dist: black ; extra == 'dev'
Requires-Dist: isort ; extra == 'dev'
Requires-Dist: pip-tools ; extra == 'dev'
Requires-Dist: pytest ; extra == 'dev'
